MANIFEST.in
README.md
setup.py
deeptoolsintervals/__init__.py
deeptoolsintervals/enrichment.py
deeptoolsintervals/parse.py
deeptoolsintervals.egg-info/PKG-INFO
deeptoolsintervals.egg-info/SOURCES.txt
deeptoolsintervals.egg-info/dependency_links.txt
deeptoolsintervals.egg-info/not-zip-safe
deeptoolsintervals.egg-info/top_level.txt
deeptoolsintervals/test/GRCh38.84.2.gtf.gz
deeptoolsintervals/test/GRCh38.84.bed
deeptoolsintervals/test/GRCh38.84.bed12.bz2
deeptoolsintervals/test/GRCh38.84.bed2
deeptoolsintervals/test/GRCh38.84.bed6
deeptoolsintervals/test/GRCh38.84.gtf.gz
deeptoolsintervals/test/GRCh38.84.labels.bed
deeptoolsintervals/test/noOverlaps.bed
deeptoolsintervals/test/strands.bed
deeptoolsintervals/tree/findOverlaps.c
deeptoolsintervals/tree/gtf.c
deeptoolsintervals/tree/gtf.h
deeptoolsintervals/tree/hashTable.c
deeptoolsintervals/tree/kseq.h
deeptoolsintervals/tree/kstring.h
deeptoolsintervals/tree/murmur3.c
deeptoolsintervals/tree/murmur3.h
deeptoolsintervals/tree/tree.c
deeptoolsintervals/tree/tree.h